{
  "id": "0e00212c-b328-4dd0-bba5-754305fa145c",
  "prevId": "629ba91b-3fd4-4f98-821d-6aaf997c774b",
  "version": "7",
  "dialect": "postgresql",
  "tables": {
    "public.tokens": {
      "name": "tokens",
      "schema": "",
      "columns": {
        "id": {
          "name": "id",
          "type": "uuid",
          "primaryKey": true,
          "notNull": true,
          "default": "gen_random_uuid()"
        },
        "user_id": {
          "name": "user_id",
          "type": "uuid",
          "primaryKey": false,
          "notNull": false
        },
        "token": {
          "name": "token",
          "type": "text",
          "primaryKey": false,
          "notNull": true
        },
        "expires_at": {
          "name": "expires_at",
          "type": "timestamp with time zone",
          "primaryKey": false,
          "notNull": true
        },
        "revoked_at": {
          "name": "revoked_at",
          "type": "timestamp with time zone",
          "primaryKey": false,
          "notNull": false
        },
        "created_at": {
          "name": "created_at",
          "type": "timestamp with time zone",
          "primaryKey": false,
          "notNull": true,
          "default": "now()"
        }
      },
      "indexes": {},
      "foreignKeys": {
        "tokens_user_id_users_id_fk": {
          "name": "tokens_user_id_users_id_fk",
          "tableFrom": "tokens",
          "tableTo": "users",
          "columnsFrom": [
            "user_id"
          ],
          "columnsTo": [
            "id"
          ],
          "onDelete": "cascade",
          "onUpdate": "no action"
        }
      },
      "compositePrimaryKeys": {},
      "uniqueConstraints": {},
      "policies": {},
      "checkConstraints": {},
      "isRLSEnabled": false
    },
    "public.users": {
      "name": "users",
      "schema": "",
      "columns": {
        "id": {
          "name": "id",
          "type": "uuid",
          "primaryKey": true,
          "notNull": true,
          "default": "gen_random_uuid()"
        },
        "username": {
          "name": "username",
          "type": "varchar(255)",
          "primaryKey": false,
          "notNull": true
        },
        "email": {
          "name": "email",
          "type": "varchar(500)",
          "primaryKey": false,
          "notNull": true
        },
        "password": {
          "name": "password",
          "type": "varchar(255)",
          "primaryKey": false,
          "notNull": true
        },
        "plan": {
          "name": "plan",
          "type": "plan",
          "typeSchema": "public",
          "primaryKey": false,
          "notNull": true,
          "default": "'FREE'"
        },
        "subscription_status": {
          "name": "subscription_status",
          "type": "subscription_status",
          "typeSchema": "public",
          "primaryKey": false,
          "notNull": true,
          "default": "'ACTIVE'"
        },
        "metadata": {
          "name": "metadata",
          "type": "jsonb",
          "primaryKey": false,
          "notNull": true,
          "default": "'{}'::jsonb"
        },
        "created_at": {
          "name": "created_at",
          "type": "timestamp",
          "primaryKey": false,
          "notNull": true,
          "default": "now()"
        },
        "updated_at": {
          "name": "updated_at",
          "type": "timestamp",
          "primaryKey": false,
          "notNull": true,
          "default": "now()"
        }
      },
      "indexes": {},
      "foreignKeys": {},
      "compositePrimaryKeys": {},
      "uniqueConstraints": {
        "users_email_unique": {
          "name": "users_email_unique",
          "nullsNotDistinct": false,
          "columns": [
            "email"
          ]
        }
      },
      "policies": {},
      "checkConstraints": {},
      "isRLSEnabled": false
    }
  },
  "enums": {
    "public.plan": {
      "name": "plan",
      "schema": "public",
      "values": [
        "FREE",
        "PRO",
        "ENTERPRISE"
      ]
    },
    "public.subscription_status": {
      "name": "subscription_status",
      "schema": "public",
      "values": [
        "ACTIVE",
        "CANCELED",
        "EXPIRED"
      ]
    }
  },
  "schemas": {},
  "sequences": {},
  "roles": {},
  "policies": {},
  "views": {},
  "_meta": {
    "columns": {},
    "schemas": {},
    "tables": {}
  }
}